wfprogressbar/__initi__.py
wfprogressbar/wfprogressbar.py
wfprogressbar-0.0.1.dist-info/LICENSE
wfprogressbar-0.0.1.dist-info/METADATA
wfprogressbar-0.0.1.dist-info/WHEEL
wfprogressbar-0.0.1.dist-info/top_level.txt
wfprogressbar-0.0.1.dist-info/RECORD
