Metadata-Version: 2.1
Name: wfprogressbar
Version: 0.0.1
Summary: A progress bar for terminal apps
Home-page: https://github.com/wyattferguson/python-progressbar
Author: Wyatt Ferguson
Author-email: wyattf@gmail.com
License: UNKNOWN
Platform: UNKNOWN
Classifier: Programming Language :: Python :: 3
Classifier: License :: OSI Approved :: MIT License
Classifier: Operating System :: OS Independent
